<?xml version="1.0" encoding="utf-8"?>
<Configuration>
  <Excluded>
    <exclude>.git</exclude>
    <exclude>1.4\Assemblies\0DubCore.dll</exclude>
    <exclude>1.4\Assemblies\0Harmony.dll</exclude>
    <exclude>1.4\Assemblies\Assembly-CSharp.dll</exclude>
    <exclude>1.4\Assemblies\Assembly-CSharp.pdb</exclude>
    <exclude>1.4\Assemblies\Assembly-CSharp-firstpass.dll</exclude>
    <exclude>1.4\Assemblies\com.rlabrecque.steamworks.net.dll</exclude>
    <exclude>1.4\Assemblies\ISharpZipLib.dll</exclude>
    <exclude>1.4\Assemblies\Mono.Posix.dll</exclude>
    <exclude>1.4\Assemblies\Mono.Security.dll</exclude>
    <exclude>1.4\Assemblies\NAudio.dll</exclude>
    <exclude>1.4\Assemblies\NVorbis.dll</exclude>
    <exclude>1.4\Assemblies\System.Configuration.dll</exclude>
    <exclude>1.4\Assemblies\System.Runtime.Serialization.dll</exclude>
    <exclude>1.4\Assemblies\System.Security.dll</exclude>
    <exclude>1.4\Assemblies\System.ServiceModel.Internals.dll</exclude>
    <exclude>1.4\Assemblies\System.Xml.Linq.dll</exclude>
    <exclude>1.4\Assemblies\Unity.TextMeshPro.dll</exclude>
    <exclude>1.4\Assemblies\UnityEngine.AccessibilityModule.dll</exclude>
    <exclude>1.4\Assemblies\UnityEngine.AIModule.dll</exclude>
    <exclude>1.4\Assemblies\UnityEngine.AndroidJNIModule.dll</exclude>
    <exclude>1.4\Assemblies\UnityEngine.AnimationModule.dll</exclude>
    <exclude>1.4\Assemblies\UnityEngine.ARModule.dll</exclude>
    <exclude>1.4\Assemblies\UnityEngine.AssetBundleModule.dll</exclude>
    <exclude>1.4\Assemblies\UnityEngine.AudioModule.dll</exclude>
    <exclude>1.4\Assemblies\UnityEngine.ClothModule.dll</exclude>
    <exclude>1.4\Assemblies\UnityEngine.ClusterInputModule.dll</exclude>
    <exclude>1.4\Assemblies\UnityEngine.ClusterRendererModule.dll</exclude>
    <exclude>1.4\Assemblies\UnityEngine.CoreModule.dll</exclude>
    <exclude>1.4\Assemblies\UnityEngine.CrashReportingModule.dll</exclude>
    <exclude>1.4\Assemblies\UnityEngine.DirectorModule.dll</exclude>
    <exclude>1.4\Assemblies\UnityEngine.dll</exclude>
    <exclude>1.4\Assemblies\UnityEngine.DSPGraphModule.dll</exclude>
    <exclude>1.4\Assemblies\UnityEngine.GameCenterModule.dll</exclude>
    <exclude>1.4\Assemblies\UnityEngine.GridModule.dll</exclude>
    <exclude>1.4\Assemblies\UnityEngine.ImageConversionModule.dll</exclude>
    <exclude>1.4\Assemblies\UnityEngine.IMGUIModule.dll</exclude>
    <exclude>1.4\Assemblies\UnityEngine.InputLegacyModule.dll</exclude>
    <exclude>1.4\Assemblies\UnityEngine.InputModule.dll</exclude>
    <exclude>1.4\Assemblies\UnityEngine.JSONSerializeModule.dll</exclude>
    <exclude>1.4\Assemblies\UnityEngine.LocalizationModule.dll</exclude>
    <exclude>1.4\Assemblies\UnityEngine.ParticleSystemModule.dll</exclude>
    <exclude>1.4\Assemblies\UnityEngine.PerformanceReportingModule.dll</exclude>
    <exclude>1.4\Assemblies\UnityEngine.Physics2DModule.dll</exclude>
    <exclude>1.4\Assemblies\UnityEngine.PhysicsModule.dll</exclude>
    <exclude>1.4\Assemblies\UnityEngine.ScreenCaptureModule.dll</exclude>
    <exclude>1.4\Assemblies\UnityEngine.SharedInternalsModule.dll</exclude>
    <exclude>1.4\Assemblies\UnityEngine.SpriteMaskModule.dll</exclude>
    <exclude>1.4\Assemblies\UnityEngine.SpriteShapeModule.dll</exclude>
    <exclude>1.4\Assemblies\UnityEngine.StreamingModule.dll</exclude>
    <exclude>1.4\Assemblies\UnityEngine.SubsystemsModule.dll</exclude>
    <exclude>1.4\Assemblies\UnityEngine.TerrainModule.dll</exclude>
    <exclude>1.4\Assemblies\UnityEngine.TerrainPhysicsModule.dll</exclude>
    <exclude>1.4\Assemblies\UnityEngine.TextCoreModule.dll</exclude>
    <exclude>1.4\Assemblies\UnityEngine.TextRenderingModule.dll</exclude>
    <exclude>1.4\Assemblies\UnityEngine.TilemapModule.dll</exclude>
    <exclude>1.4\Assemblies\UnityEngine.UI.dll</exclude>
    <exclude>1.4\Assemblies\UnityEngine.UIElementsModule.dll</exclude>
    <exclude>1.4\Assemblies\UnityEngine.UIModule.dll</exclude>
    <exclude>1.4\Assemblies\UnityEngine.UNETModule.dll</exclude>
    <exclude>1.4\Assemblies\UnityEngine.UnityAnalyticsModule.dll</exclude>
    <exclude>1.4\Assemblies\UnityEngine.UnityConnectModule.dll</exclude>
    <exclude>1.4\Assemblies\UnityEngine.UnityWebRequestAssetBundleModule.dll</exclude>
    <exclude>1.4\Assemblies\UnityEngine.UnityWebRequestAudioModule.dll</exclude>
    <exclude>1.4\Assemblies\UnityEngine.UnityWebRequestModule.dll</exclude>
    <exclude>1.4\Assemblies\UnityEngine.UnityWebRequestTextureModule.dll</exclude>
    <exclude>1.4\Assemblies\UnityEngine.UnityWebRequestWWWModule.dll</exclude>
    <exclude>1.4\Assemblies\UnityEngine.VehiclesModule.dll</exclude>
    <exclude>1.4\Assemblies\UnityEngine.VFXModule.dll</exclude>
    <exclude>1.4\Assemblies\UnityEngine.VideoModule.dll</exclude>
    <exclude>1.4\Assemblies\UnityEngine.VRModule.dll</exclude>
    <exclude>1.4\Assemblies\UnityEngine.WindModule.dll</exclude>
    <exclude>1.4\Assemblies\UnityEngine.XRModule.dll</exclude>
    <exclude>About\preview.afdesign</exclude>
    <exclude>README.md</exclude>
    <exclude>Source</exclude>
    <exclude>spanish.zip</exclude>
    <exclude>Textures\UI\Commands\PSDs</exclude>
  </Excluded>
</Configuration>